[{"__type__":"cc.SpriteFrame","content":{"name":"pai-beimian","texture":"d8jhfOi5ZFl5jHBpDy5cDo","rect":[1,192,137,189],"offset":[0,0],"originalSize":[137,189]}},[{"__type__":"cc.Prefab","_name":"ymn-pokerback","data":{"__id__":1},"asyncLoadAssets":null},{"__type__":"cc.Node","_name":"pai-beimian","_components":[{"__type__":"cc.Sprite","node":{"__id__":1},"_spriteFrame":{"__uuid__":"98p/wnlZVHf4TU4XSxcL33"}}],"_prefab":{"__type__":"cc.PrefabInfo","root":{"__id__":1},"asset":{"__uuid__":"f3C11jhSRLbr0s+Fsm/Czr"},"fileId":"72sKSnrEBI7JNZOXFNhXBm"},"_contentSize":{"__type__":"cc.Size","width":137,"height":189},"_position":{"__type__":"cc.Vec2","x":348,"y":246}}]]